enscons/__init__.py
enscons/api.py
enscons/cli.py
enscons/cpyext.py
enscons/helpers.py
enscons/paths.py
enscons/pytar.py
enscons/setup.py
enscons/setup2toml.py
enscons/util.py
enscons/SConstruct.in
enscons_forked-0.28.0.dist-info/METADATA
enscons_forked-0.28.0.dist-info/WHEEL
enscons_forked-0.28.0.dist-info/entry_points.txt
enscons_forked-0.28.0.dist-info/RECORD