Metadata-Version: 2.1
Name: enscons-forked
Version: 0.28.0
Summary: Tools for building Python packages with SCons (forked for providing some useful features)
License: MIT
Author: Christoph Wiedemann
Author-email: 62332054+cwiede@users.noreply.github.com
Keywords: packaging,wheel
Classifier: Programming Language :: Python :: 2.7
Classifier: Programming Language :: Python :: 3
Home-Page: https://github.com/cwiede/enscons
Provides-Extra: cli
Requires-Dist: click; extra == 'cli'
Provides-Extra: docs
Requires-Dist: furo; extra == 'docs'
Requires-Dist: sphinx; extra == 'docs'
Requires-Dist: myst-parser; extra == 'docs'
Requires-Dist: mdit-py-plugins>=0.3.0; extra == 'docs'
Requires-Dist: scons>=3.0.5
Requires-Dist: pytoml>=0.1
Requires-Dist: setuptools
Requires-Dist: wheel
Requires-Dist: attrs
Requires-Dist: packaging>=20.9
Requires-Dist: editables==0.2; python_version > "3.0"
